HMpTy/.DS_Store
HMpTy/__init__.py
HMpTy/__version__.py
HMpTy/cl_utils.py
HMpTy/default_settings.yaml
HMpTy/test_settings.yaml
HMpTy/utKit.py
HMpTy/commonutils/__init__.py
HMpTy/commonutils/getpackagepath.py
HMpTy/htm/__init__.py
HMpTy/htm/_htmc.cpython-311-darwin.so
HMpTy/htm/_htmc.cpython-312-darwin.so
HMpTy/htm/_htmc.cpython-39-darwin.so
HMpTy/htm/_htmcCode.py
HMpTy/htm/htm.py
HMpTy/htm/htmc.cc
HMpTy/htm/htmc.h
HMpTy/htm/htmc.i
HMpTy/htm/htmc_wrap-backup.cc
HMpTy/htm/htmc_wrap.cc
HMpTy/htm/runswig.sh
HMpTy/htm/sets.py
HMpTy/htm/htm_src/BitList.cpp
HMpTy/htm/htm_src/BitList.h
HMpTy/htm/htm_src/BitList.hxx
HMpTy/htm/htm_src/SConscript
HMpTy/htm/htm_src/SpatialConstraint.cpp
HMpTy/htm/htm_src/SpatialConstraint.h
HMpTy/htm/htm_src/SpatialConstraint.hxx
HMpTy/htm/htm_src/SpatialConvex.cpp
HMpTy/htm/htm_src/SpatialConvex.h
HMpTy/htm/htm_src/SpatialConvex.hxx
HMpTy/htm/htm_src/SpatialDoc.h
HMpTy/htm/htm_src/SpatialDomain.cpp
HMpTy/htm/htm_src/SpatialDomain.h
HMpTy/htm/htm_src/SpatialDomain.hxx
HMpTy/htm/htm_src/SpatialEdge.cpp
HMpTy/htm/htm_src/SpatialEdge.h
HMpTy/htm/htm_src/SpatialException.cpp
HMpTy/htm/htm_src/SpatialException.h
HMpTy/htm/htm_src/SpatialGeneral.h
HMpTy/htm/htm_src/SpatialIndex.cpp
HMpTy/htm/htm_src/SpatialIndex.h
HMpTy/htm/htm_src/SpatialIndex.hxx
HMpTy/htm/htm_src/SpatialIndexTcl.h
HMpTy/htm/htm_src/SpatialInterface.cpp
HMpTy/htm/htm_src/SpatialInterface.h
HMpTy/htm/htm_src/SpatialInterface.hxx
HMpTy/htm/htm_src/SpatialMarkup.h
HMpTy/htm/htm_src/SpatialVector.cpp
HMpTy/htm/htm_src/SpatialVector.h
HMpTy/htm/htm_src/SpatialVector.hxx
HMpTy/htm/htm_src/VarStr.cpp
HMpTy/htm/htm_src/VarStr.h
HMpTy/htm/htm_src/VarVec.h
HMpTy/htm/htm_src/classHeader.inc
HMpTy/htm/htm_src/hierHeader.inc
HMpTy/htm/htm_src/indexHeader.inc
HMpTy/include/NumpyRecords.h
HMpTy/include/NumpyVector.h
HMpTy/include/NumpyVoidVector.h
HMpTy/mysql/__init__.py
HMpTy/mysql/add_htm_ids_to_mysql_database_table.py
HMpTy/mysql/conesearch.py
HMpTy/resources/package.mplstyle
hmpty-1.8.0.dist-info/licenses/LICENSE
hmpty-1.8.0.dist-info/METADATA
hmpty-1.8.0.dist-info/WHEEL
hmpty-1.8.0.dist-info/entry_points.txt
hmpty-1.8.0.dist-info/top_level.txt
hmpty-1.8.0.dist-info/RECORD
