Metadata-Version: 2.4
Name: HMpTy
Version: 1.8.0
Summary: Generate Hierarchical Triangular Mesh (HTM) IDs, crossmatch sets of sky-coordinates and more
Home-page: https://github.com/thespacedoctor/HMpTy
Download-URL: https://github.com/thespacedoctor/HMpTy/archive/v1.8.0.zip
Author: David Young
Author-email: davidrobertyoung@gmail.com
License: GNU
Keywords: astronomy, crossmatch, htm
Classifier: Development Status :: 4 - Beta
Classifier: License :: OSI Approved :: MIT License
Classifier: Programming Language :: Python :: 3.7
Classifier: Topic :: Utilities
License-File: LICENSE
Requires-Dist: pyyaml
Requires-Dist: HMpTy
Requires-Dist: fundamentals
Requires-Dist: docopt
Requires-Dist: astrocalc
Requires-Dist: multiprocess
Requires-Dist: unicodecsv
Requires-Dist: pandas
Requires-Dist: pymysql
Requires-Dist: scipy
Dynamic: author
Dynamic: author-email
Dynamic: classifier
Dynamic: description
Dynamic: description-content-type
Dynamic: download-url
Dynamic: home-page
Dynamic: keywords
Dynamic: license
Dynamic: license-file
Dynamic: requires-dist
Dynamic: summary
